jobstruct/__init__.py
jobstruct/__main__.py
jobstruct/jobstructai.py
jobstruct/jobstructhtml.py
jobstruct/prompts.py
jobstruct/py.typed
jobstruct/skillsnode.py
jobstruct/skillstaxonomyai.py
jobstruct/data/__init__.py
jobstruct/data/onet_taxonomy.json
jobstruct/data/onet_taxonomy_renamed.json
jobstruct/data/onet_taxonomy_renamed.py
jobstruct/data/prompt_configs.json
jobstruct-0.1.1.dist-info/LICENSE.txt
jobstruct-0.1.1.dist-info/METADATA
jobstruct-0.1.1.dist-info/WHEEL
jobstruct-0.1.1.dist-info/entry_points.txt
jobstruct-0.1.1.dist-info/top_level.txt
jobstruct-0.1.1.dist-info/RECORD
