Metadata-Version: 2.1
Name: jobstruct
Version: 0.1.1
Summary: Extract structured information from job postings.
Home-page: https://github.com/amazon-science/job-posting-structure
Author: Mark Howison
Author-email: mhowison@amazon.com
License: CC-BY-NC-SA-4.0
Classifier: Development Status :: 3 - Alpha
Classifier: License :: Free for non-commercial use
Classifier: Intended Audience :: Science/Research
Classifier: Operating System :: OS Independent
Classifier: Natural Language :: English
Classifier: Programming Language :: Python :: 3
Classifier: Topic :: Scientific/Engineering
Classifier: Topic :: Scientific/Engineering :: Artificial Intelligence
Classifier: Topic :: Scientific/Engineering :: Information Analysis
Requires-Python: >=3.8
License-File: LICENSE.txt
Requires-Dist: beautifulsoup4 >=4.0.0
Requires-Dist: boto3 >=1.35.1
Requires-Dist: boto3-stubs-lite[bedrock-runtime] >=1.35.1
